README.md
setup.py
ValidationRules/__init__.py
ValidationRules/dateTimeHandler.py
ValidationRules/fieldRules.py
ValidationRules/reRuleMatch.py
ValidationRules/ruleHandler.py
ValidationRules/structureFunc.py
python_validation_rules.egg-info/PKG-INFO
python_validation_rules.egg-info/SOURCES.txt
python_validation_rules.egg-info/dependency_links.txt
python_validation_rules.egg-info/requires.txt
python_validation_rules.egg-info/top_level.txt