Metadata-Version: 2.1
Name: python-validation-rules
Version: 0.1.17
Summary: UNKNOWN
Home-page: https://github.com/Gaoshengyue/validationRules
Author: Symoon
Author-email: symoon.gao@gmail.com
License: MIT
Download-URL: https://github.com/Gaoshengyue/validationRules/releases/tag/v0.1.17
Keywords: python-validation-rules,validation-rules
Platform: UNKNOWN
Classifier: License :: OSI Approved :: MIT License
Classifier: Programming Language :: Python
Classifier: Intended Audience :: Developers
Classifier: Operating System :: OS Independent
